Examples/Ex02/ex02.v
module ex02(
    input A,
    input B,
    input C,
    output P,
    output Q);

    assign P = (A & B & C);
    assign Q = ((A & B) + C);

endmodule

Examples/Ex02/ex02tb.v
`timescale 1ps/1ps
`include "ex02.v"

module ex02tb;
    reg A;
    reg B;
    reg C;
    wire P;
    wire Q;

    ex02 uut  (.A(A), .B(B), .C(C), .P(P), .Q(Q));

    initial begin
        $dumpfile("DumpEx02.vcd");
        $dumpvars();

        A = 0; B = 0; C = 0; 
        #20 C = 1;
        #20 C = 0; B=1;
        #20 C = 1;
        #20 C = 0; B=0; A=1;
        #20 C = 1;
        #20 C = 0; B=1;
        #20 C = 1;
    end

    initial begin
    $monitor("time =%2d A=%b B=%b C=%b P=%b Q=%b", $time,A,B,C,P,Q);
end

endmodule

Examples/Ex02/build/DumpEx02.vcd
$date
	Mon Feb 19 09:14:35 2024
$end
$version
	Icarus Verilog
$end
$timescale
	1ps
$end
$scope module ex02tb $end
$var wire 1 ! Q $end
$var wire 1 " P $end
$var reg 1 # A $end
$var reg 1 $ B $end
$var reg 1 % C $end
$scope module uut $end
$var wire 1 # A $end
$var wire 1 $ B $end
$var wire 1 % C $end
$var wire 1 " P $end
$var wire 1 ! Q $end
$upscope $end
$upscope $end
$enddefinitions $end
$comment Show the parameter values. $end
$dumpall
$end
#0
$dumpvars
0%
0$
0#
0"
0!
$end
#20
1!
1%
#40
1$
0!
0%
#60
1!
1%
#80
1#
0$
0!
0%
#100
1!
1%
#120
1$
1!
0%
#140
1"
0!
1%
