Examples/Ex01_SimpleInOut/ex01.v
// Simple in and out 

module ex01(
    input A,
    input B,
    input C,
    output P,
    output Q);

    assign P = (A & B & C);
    assign Q = (A | B | C);

endmodule

Examples/Ex01/ex01tb.v
`timescale 1ns/1ps
`include "ex01.v"

module ex01tb;  // No input No Output 
    reg A;
    reg B;
    reg C;
    wire P;
    wire Q;

    ex01 uut  (.A(A), .B(B), .C(C), .P(P), .Q(Q)); // Copy of Ex01.v (if you want another uut can be added)

    initial begin
        $dumpfile("DumpEx01.vcd");
        $dumpvars();

        A = 0; B = 0; C = 0; 
        #20 C = 1;
        #20 C = 0; B=1;
        #20 C = 1;
        #20 C = 0; B=0; A=1;
        #20 C = 1;
        #20 C = 0; B=1;
        #20 C = 1;
    end

    initial begin
    $monitor("time =%2d A=%b B=%b C=%b P=%b Q=%b", $time,A,B,C,P,Q);
end

endmodule

Examples/Ex01/build/DumpEx01.vcd
$date
	Mon Feb 19 09:13:19 2024
$end
$version
	Icarus Verilog
$end
$timescale
	1ps
$end
$scope module ex01tb $end
$var wire 1 ! Q $end
$var wire 1 " P $end
$var reg 1 # A $end
$var reg 1 $ B $end
$var reg 1 % C $end
$scope module uut $end
$var wire 1 # A $end
$var wire 1 $ B $end
$var wire 1 % C $end
$var wire 1 " P $end
$var wire 1 ! Q $end
$upscope $end
$upscope $end
$enddefinitions $end
$comment Show the parameter values. $end
$dumpall
$end
#0
$dumpvars
0%
0$
0#
0"
0!
$end
#20
1!
1%
#40
1!
1$
0%
#60
1%
#80
1#
0$
0%
#100
1%
#120
1$
0%
#140
1"
1%
