01_Comparator/comp20.v
// 2-bit comparator

module comp20 (
    input [1:0]x,
    input [1:0]y,
    output z);

assign z = ( ~x[0] & ~x[1] & ~y[0] & ~y[1] ) | 
            ( ~x[0] & x[1] & ~y[0] & y[1] ) |
            ( x[0] & x[1] & y[0] & y[1] ) |
            ( x[0] & ~x[1] & y[0] & ~y[1] );

endmodule

01_Comparator/comp20tb.v
`timescale 1ns/1ps  
`include "comp20.v"

module comp20tb;
    reg [1:0]x;
    reg [1:0]y;
    wire z;

    // Instantiate the unit under test
    comp20 uut( .x(x), .y(y), .z(z));

    initial begin
        $dumpfile("dumpCom20.vcd");
        $dumpvars;

        x=2'b00; y=2'b00;
        #20 y=2'b01;
        #20 y=2'b10;
        #20 y=2'b11;

        #20 x=2'b01; y=2'b00;
        #20 y=2'b01;
        #20 y=2'b10;
        #20 y=2'b11;

        #20 x=2'b10; y=2'b00;
        #20 y=2'b01;
        #20 y=2'b10;
        #20 y=2'b11;

        #20 x=2'b11; y=2'b00;
        #20 y=2'b01;
        #20 y=2'b10;
        #20 y=2'b11;

    end

initial begin
    $monitor("time =%2d x=%2b y=%2b z=%b", $time,x,y,z);
end

endmodule

01_Comparator/build/dumpCom20.vcd
$date
	Mon Feb 12 05:50:17 2024
$end
$version
	Icarus Verilog
$end
$timescale
	1ps
$end
$scope module comp20tb $end
$var wire 1 ! z $end
$var reg 2 " x [1:0] $end
$var reg 2 # y [1:0] $end
$scope module uut $end
$var wire 2 $ x [1:0] $end
$var wire 2 % y [1:0] $end
$var wire 1 ! z $end
$upscope $end
$upscope $end
$enddefinitions $end
$comment Show the parameter values. $end
$dumpall
$end
#0
$dumpvars
b0 %
b0 $
b0 #
b0 "
1!
$end
#20000
0!
b1 #
b1 %
#40000
b10 #
b10 %
#60000
b11 #
b11 %
#80000
b0 #
b0 %
b1 "
b1 $
#100000
1!
b1 #
b1 %
#120000
0!
b10 #
b10 %
#140000
b11 #
b11 %
#160000
b0 #
b0 %
b10 "
b10 $
#180000
b1 #
b1 %
#200000
1!
b10 #
b10 %
#220000
0!
b11 #
b11 %
#240000
b0 #
b0 %
b11 "
b11 $
#260000
b1 #
b1 %
#280000
0!
b10 #
b10 %
#300000
1!
b11 #
b11 %
